{
  "url": "https://www.californiaclosets.ca/en/living-area/entryways/",
  "requestedUrl": "https://www.californiaclosets.ca/en/living-area/entryways/",
  "timestamp": 1691930374923,
  "ranks": {
    "hundos": 23,
    "performance": 24,
    "accessibility": 12,
    "cumulative": 23
  },
  "lighthouse": {
    "version": "9.6.8",
    "performance": 0.25,
    "accessibility": 0.91,
    "bestPractices": 0.92,
    "seo": 0.83,
    "total": 291
  },
  "firstContentfulPaint": 3291.4160000000006,
  "firstMeaningfulPaint": 3291.4160000000006,
  "speedIndex": 7815.424757240886,
  "largestContentfulPaint": 11059.142000000003,
  "totalBlockingTime": 1193,
  "cumulativeLayoutShift": 0.15019918208652072,
  "timeToInteractive": 13814.973,
  "maxPotentialFirstInputDelay": 474,
  "timeToFirstByte": 2236.574,
  "weight": {
    "summary": "169 requests • 2,883 KiB",
    "total": 2952169,
    "image": 1347787,
    "imageCount": 64,
    "script": 1192896,
    "scriptCount": 62,
    "document": 70731,
    "font": 221347,
    "fontCount": 11,
    "stylesheet": 116209,
    "stylesheetCount": 19,
    "thirdParty": 2602656,
    "thirdPartyCount": 114
  },
  "run": {
    "number": 2,
    "total": 3
  },
  "sidequests": {
    "-weight.total": 13,
    "+weight.total": 13,
    "-weight.document": 21,
    "+weight.document": 5,
    "-weight.script": 18,
    "+weight.script": 8,
    "-weight.image": 12,
    "+weight.image": 14,
    "-weight.font": 21,
    "+weight.font": 5,
    "+weight.fontCount": 2,
    "-timeToFirstByte": 22,
    "-totalBlockingTime": 22,
    "-largestContentfulPaint": 25
  },
  "axe": {
    "passes": 1853,
    "violations": 39
  }
}