{
  "url": "https://www.californiaclosets.com/home-office/",
  "requestedUrl": "https://www.californiaclosets.com/home-office/",
  "timestamp": 1708866202168,
  "ranks": {
    "hundos": 37,
    "performance": 37,
    "accessibility": 14,
    "cumulative": 37
  },
  "lighthouse": {
    "version": "9.6.8",
    "performance": 0.45,
    "accessibility": 0.83,
    "bestPractices": 0.92,
    "seo": 0.9,
    "total": 310
  },
  "firstContentfulPaint": 3214.6949999999997,
  "firstMeaningfulPaint": 3214.6949999999997,
  "speedIndex": 6562.692259447903,
  "largestContentfulPaint": 4656.125,
  "totalBlockingTime": 673.5,
  "cumulativeLayoutShift": 0.005222478866577149,
  "timeToInteractive": 17764.099000000006,
  "maxPotentialFirstInputDelay": 224,
  "timeToFirstByte": 15.752000000000002,
  "weight": {
    "summary": "138 requests • 2,815 KiB",
    "total": 2882424,
    "image": 837355,
    "imageCount": 45,
    "script": 1337891,
    "scriptCount": 53,
    "document": 126854,
    "font": 295198,
    "fontCount": 14,
    "stylesheet": 228907,
    "stylesheetCount": 6,
    "thirdParty": 2367218,
    "thirdPartyCount": 80
  },
  "run": {
    "number": 2,
    "total": 3
  },
  "sidequests": {
    "-weight.total": 36,
    "+weight.total": 2,
    "-weight.document": 36,
    "+weight.document": 1,
    "-weight.script": 36,
    "+weight.script": 2,
    "-weight.image": 32,
    "+weight.image": 6,
    "-weight.font": 34,
    "+weight.font": 2,
    "+weight.fontCount": 1,
    "-timeToFirstByte": 28,
    "-totalBlockingTime": 36,
    "-largestContentfulPaint": 30
  },
  "axe": {
    "passes": 1066,
    "violations": 5
  }
}