{
  "url": "https://www.californiaclosets.ca/en/how-we-work/design-to-your-budget/",
  "requestedUrl": "https://www.californiaclosets.ca/en/how-we-work/design-to-your-budget/",
  "timestamp": 1693744808717,
  "ranks": {
    "hundos": 25,
    "performance": 10,
    "accessibility": 25,
    "cumulative": 25
  },
  "lighthouse": {
    "version": "9.6.8",
    "performance": 0.45,
    "accessibility": 0.77,
    "bestPractices": 0.92,
    "seo": 0.75,
    "total": 289
  },
  "firstContentfulPaint": 2940.7819999999997,
  "firstMeaningfulPaint": 3844.1460000000006,
  "speedIndex": 5967.240763008006,
  "largestContentfulPaint": 5182.736499999999,
  "totalBlockingTime": 789.0000000000009,
  "cumulativeLayoutShift": 0.038829973644680445,
  "timeToInteractive": 9504.0665,
  "maxPotentialFirstInputDelay": 290,
  "timeToFirstByte": 1733.011,
  "weight": {
    "summary": "138 requests • 5,258 KiB",
    "total": 5384035,
    "image": 4332116,
    "imageCount": 54,
    "script": 666387,
    "scriptCount": 46,
    "document": 63028,
    "font": 203870,
    "fontCount": 10,
    "stylesheet": 115838,
    "stylesheetCount": 18,
    "thirdParty": 5042854,
    "thirdPartyCount": 86
  },
  "run": {
    "number": 2,
    "total": 3
  },
  "sidequests": {
    "-weight.total": 23,
    "+weight.total": 3,
    "-weight.document": 9,
    "+weight.document": 17,
    "-weight.script": 19,
    "+weight.script": 7,
    "-weight.image": 23,
    "+weight.image": 3,
    "-weight.font": 8,
    "+weight.font": 18,
    "+weight.fontCount": 3,
    "-timeToFirstByte": 16,
    "-totalBlockingTime": 14,
    "-largestContentfulPaint": 7
  },
  "axe": {
    "passes": 1438,
    "violations": 37
  }
}